tap_streamduo/__init__.py
tap_streamduo/schemas/records.json
tap_streamduo-0.1.0.dist-info/LICENSE
tap_streamduo-0.1.0.dist-info/METADATA
tap_streamduo-0.1.0.dist-info/WHEEL
tap_streamduo-0.1.0.dist-info/entry_points.txt
tap_streamduo-0.1.0.dist-info/top_level.txt
tap_streamduo-0.1.0.dist-info/RECORD
