Metadata-Version: 2.1
Name: tap-streamduo
Version: 0.1.0
Summary: Singer.io tap for extracting data from StreamDuo streams
Home-page: https://streamduo.com
Author: StreamDuo
License: UNKNOWN
Platform: UNKNOWN
Classifier: Programming Language :: Python :: 3 :: Only
License-File: LICENSE
Requires-Dist: singer-python (==5.12.2)
Requires-Dist: streamduo (==0.0.22)
